Metadata-Version: 1.1
Name: cannyfier
Version: 0.2.10
Summary: Show canny on any part of the screen. Better to use with video
Home-page: UNKNOWN
Author: Pascual Martinez
Author-email: pascual.martinezzapata@gmail.com
License: MIT
Platform: UNKNOWN
Classifier: Programming Language :: Python :: 3
Classifier: License :: OSI Approved :: MIT License
Classifier: Operating System :: OS Independent
